pdlpy/__init__.py
pdlpy/bernoulli.py
pdlpy/binomial.py
pdlpy/decorators.py
pdlpy/distribution.py
pdlpy/exponential.py
pdlpy/geometric.py
pdlpy/hypergeometric.py
pdlpy/math.py
pdlpy/normal.py
pdlpy/poisson.py
pdlpy/uniform.py
pdlpy-0.4.1.dist-info/LICENSE
pdlpy-0.4.1.dist-info/METADATA
pdlpy-0.4.1.dist-info/WHEEL
pdlpy-0.4.1.dist-info/top_level.txt
pdlpy-0.4.1.dist-info/RECORD
